{
  "date": "2026-04-27",
  "items": [
    {
      "ticker": "0050",
      "name": "元大台灣50",
      "aum_yi": 16612.1
    },
    {
      "ticker": "0056",
      "name": "元大高股息",
      "aum_yi": 5835.7
    },
    {
      "ticker": "00878",
      "name": "國泰永續高股息",
      "aum_yi": 4840.8
    },
    {
      "ticker": "00919",
      "name": "群益台灣精選高息",
      "aum_yi": 4508.6
    },
    {
      "ticker": "006208",
      "name": "富邦台50",
      "aum_yi": 3887.8
    },
    {
      "ticker": "00937B",
      "name": "群益ESG投等債20+",
      "aum_yi": 2678.9
    },
    {
      "ticker": "00981A",
      "name": "主動統一台股增長",
      "aum_yi": 2120.8
    },
    {
      "ticker": "00679B",
      "name": "元大美債20年",
      "aum_yi": 2037.1
    },
    {
      "ticker": "00751B",
      "name": "元大AAA至A公司債",
      "aum_yi": 1676.6
    },
    {
      "ticker": "00687B",
      "name": "國泰20年美債",
      "aum_yi": 1623.3
    },
    {
      "ticker": "00720B",
      "name": "元大投資級公司債",
      "aum_yi": 1341.1
    },
    {
      "ticker": "00725B",
      "name": "國泰投資級公司債",
      "aum_yi": 1333.7
    },
    {
      "ticker": "0052",
      "name": "富邦科技",
      "aum_yi": 1318.6
    },
    {
      "ticker": "00772B",
      "name": "中信高評級公司債",
      "aum_yi": 1171.9
    },
    {
      "ticker": "00929",
      "name": "復華台灣科技優息",
      "aum_yi": 1136.6
    }
  ]
}